sytk/__init__.py
sytk/debug.py
sytk/hack.py
sytk/logger.py
sytk/print2file.py
sytk/timer.py
sytk/ez_parser/__init__.py
sytk/ez_parser/element.py
sytk/ez_parser/ez_parser.py
sytk-0.3.2.dist-info/LICENSE
sytk-0.3.2.dist-info/METADATA
sytk-0.3.2.dist-info/WHEEL
sytk-0.3.2.dist-info/top_level.txt
sytk-0.3.2.dist-info/RECORD
