Metadata-Version: 2.1
Name: sytk
Version: 0.3.2
Summary: Some tools making life a little easier :)
Home-page: https://github.com/universuen/sytk
Author: universuen
Author-email: universuen@gmail.com
License: UNKNOWN
Platform: UNKNOWN
Classifier: Programming Language :: Python :: 3
Classifier: License :: OSI Approved :: MIT License
Classifier: Operating System :: OS Independent
Requires-Python: >=3.7
License-File: LICENSE
